ecodev_model/__init__.py
ecodev_model/emission_type.py
ecodev_model/sector.py
ecodev_model/units.py
ecodev_model-0.0.1.dist-info/METADATA
ecodev_model-0.0.1.dist-info/WHEEL
ecodev_model-0.0.1.dist-info/RECORD
