Metadata-Version: 2.1
Name: ecodev-model
Version: 0.0.1
Summary: emission domain model
Author: Thomas Epelbaum
Author-email: tomepel@gmail.com
Requires-Python: >=3.11,<4.0
Classifier: Programming Language :: Python :: 3
Classifier: Programming Language :: Python :: 3.11
Classifier: Programming Language :: Python :: 3.12
